batchflow/__init__.py
batchflow/_const.py
batchflow/base.py
batchflow/batch.py
batchflow/batch_image.py
batchflow/components.py
batchflow/config.py
batchflow/dataset.py
batchflow/decorators.py
batchflow/dsindex.py
batchflow/exceptions.py
batchflow/model_dir.py
batchflow/monitor.py
batchflow/named_expr.py
batchflow/notifier.py
batchflow/once_pipeline.py
batchflow/pipeline.py
batchflow/pipeline_executor.py
batchflow/profiler.py
batchflow/sampler.py
batchflow/utils.py
batchflow/utils_import.py
batchflow/utils_notebook.py
batchflow/utils_random.py
batchflow/utils_telegram.py
batchflow/utils_transforms.py
batchflow/variables.py
batchflow/models/__init__.py
batchflow/models/base.py
batchflow/models/sklearn.py
batchflow/models/utils.py
batchflow/models/metrics/__init__.py
batchflow/models/metrics/base.py
batchflow/models/metrics/classify.py
batchflow/models/metrics/loss.py
batchflow/models/metrics/regression.py
batchflow/models/metrics/segment.py
batchflow/models/metrics/utils.py
batchflow/models/torch/README.md
batchflow/models/torch/__init__.py
batchflow/models/torch/base.py
batchflow/models/torch/base_batchsize_mixin.py
batchflow/models/torch/base_mixins.py
batchflow/models/torch/benchmark.py
batchflow/models/torch/densenet.py
batchflow/models/torch/efficientnet.py
batchflow/models/torch/initialization.py
batchflow/models/torch/network.py
batchflow/models/torch/repr_mixin.py
batchflow/models/torch/resnest.py
batchflow/models/torch/resnet.py
batchflow/models/torch/unet.py
batchflow/models/torch/utils.py
batchflow/models/torch/vgg.py
batchflow/models/torch/blocks/__init__.py
batchflow/models/torch/blocks/attention.py
batchflow/models/torch/blocks/core.py
batchflow/models/torch/blocks/named_blocks.py
batchflow/models/torch/blocks/pyramid.py
batchflow/models/torch/blocks/transformer_blocks.py
batchflow/models/torch/callbacks/__init__.py
batchflow/models/torch/callbacks/base.py
batchflow/models/torch/callbacks/plateau.py
batchflow/models/torch/layers/__init__.py
batchflow-0.9.4.dist-info/METADATA
batchflow-0.9.4.dist-info/WHEEL
batchflow-0.9.4.dist-info/licenses/LICENSE
batchflow-0.9.4.dist-info/RECORD
