Metadata-Version: 2.4
Name: batchflow
Version: 0.9.4
Summary: ML pipelines, model configuration and batch management
Author-email: Roman Kh <rhudor@gmail.com>
License: Apache License 2.0
License-File: LICENSE
Classifier: Development Status :: 4 - Beta
Classifier: Intended Audience :: Developers
Classifier: Intended Audience :: Science/Research
Classifier: License :: OSI Approved :: Apache Software License
Classifier: Operating System :: OS Independent
Classifier: Programming Language :: Python
Classifier: Programming Language :: Python :: 3
Classifier: Programming Language :: Python :: 3.10
Classifier: Topic :: Scientific/Engineering
Requires-Python: >=3.10
Requires-Dist: dill>=0.3
Requires-Dist: llvmlite
Requires-Dist: numba>=0.56
Requires-Dist: numpy>=1.26
Requires-Dist: scipy>=1.9
Requires-Dist: tqdm>=4.19
Provides-Extra: dev
Requires-Dist: pandas>=0.24; extra == 'dev'
Requires-Dist: pytest>=8.3.4; extra == 'dev'
Requires-Dist: ruff; extra == 'dev'
Provides-Extra: image
Requires-Dist: matplotlib>=3.7; extra == 'image'
Requires-Dist: pillow<11.0,>=9.4; extra == 'image'
Provides-Extra: jupyter
Requires-Dist: ipykernel; extra == 'jupyter'
Requires-Dist: ipython; extra == 'jupyter'
Requires-Dist: jupyter-client; extra == 'jupyter'
Requires-Dist: jupyter-server; extra == 'jupyter'
Requires-Dist: nbconvert; extra == 'jupyter'
Requires-Dist: nbformat; extra == 'jupyter'
Requires-Dist: notebook; extra == 'jupyter'
Requires-Dist: requests; extra == 'jupyter'
Provides-Extra: monitor
Requires-Dist: nvidia-ml-py; extra == 'monitor'
Requires-Dist: psutil; extra == 'monitor'
Provides-Extra: nn
Requires-Dist: einops>=0.3; extra == 'nn'
Requires-Dist: ptflops>=0.6; extra == 'nn'
Requires-Dist: scikit-learn>=0.21.3; extra == 'nn'
Requires-Dist: torch>=1.13; extra == 'nn'
Requires-Dist: torchvision>=0.14; extra == 'nn'
Provides-Extra: onnx
Requires-Dist: onnx2torch>=1.5.0; extra == 'onnx'
Requires-Dist: onnx>=1.14.0; extra == 'onnx'
Provides-Extra: openvino
Requires-Dist: openvino>=2025.0.0; extra == 'openvino'
Provides-Extra: other
Requires-Dist: urllib3>=1.25; extra == 'other'
Provides-Extra: research
Requires-Dist: multiprocess>=0.70; extra == 'research'
Requires-Dist: py-nbtools>=0.9.15; extra == 'research'
Provides-Extra: safetensors
Requires-Dist: safetensors>=0.5.3; extra == 'safetensors'
Provides-Extra: telegram
Requires-Dist: pillow<11.0,>=9.4; extra == 'telegram'
